langroom/__init__.py
langroom/assets/ball.png
langroom/assets/floor.png
langroom/assets/player.png
langroom/assets/rug.png
langroom/assets/table.png
langroom/assets/vase.png
langroom/assets/wall.png
langroom/embodied.py
langroom/langroom.py
langroom-0.1.2.dist-info/METADATA
langroom-0.1.2.dist-info/WHEEL
langroom-0.1.2.dist-info/RECORD
