Metadata-Version: 2.1
Name: langroom
Version: 0.1.2
Summary: A minimal gridworld environment for embodied question answering.
Keywords: environment,agent,rl,language
Author: Jessy Lin
Author-email: jessy81697@gmail.com
Requires-Python: >=3.8,<4.0
Classifier: Programming Language :: Python :: 3
Classifier: Programming Language :: Python :: 3.8
Classifier: Programming Language :: Python :: 3.9
Classifier: Programming Language :: Python :: 3.10
Classifier: Programming Language :: Python :: 3.11
Requires-Dist: Pillow
Requires-Dist: imageio
Requires-Dist: numpy
Requires-Dist: pygame
